README.md
setup.py
TOPSIS_RATISH_101803004.egg-info/PKG-INFO
TOPSIS_RATISH_101803004.egg-info/SOURCES.txt
TOPSIS_RATISH_101803004.egg-info/dependency_links.txt
TOPSIS_RATISH_101803004.egg-info/requires.txt
TOPSIS_RATISH_101803004.egg-info/top_level.txt
src/topsis.py