Metadata-Version: 2.1
Name: TOPSIS-RATISH-101803004
Version: 1.0.0
Summary: A Python package implementing TOPSIS technique.
Home-page: https://github.com/gpriya32/TOPSIS-PriyankaGupta-101803006/
Author: RATISH JINDAL
Author-email: JINDALRATISH@gmail.com
License: MIT
Download-URL: https://github.com/gpriya32/TOPSIS-PriyankaGupta-101803006/archive/1.0.0.tar.gz
Platform: UNKNOWN
